Framework/__init__.py
Framework/myhelp.py
myhelppack-0.0.2.dist-info/LICENSE
myhelppack-0.0.2.dist-info/METADATA
myhelppack-0.0.2.dist-info/WHEEL
myhelppack-0.0.2.dist-info/top_level.txt
myhelppack-0.0.2.dist-info/RECORD
