Metadata-Version: 2.1
Name: myhelppack
Version: 0.0.2
Summary: MyHelp Package
Home-page: https://github.com/TFDevCycle/MyHelp
Author: Tony Frerich
Author-email: tfdevcycle@gmail.com
License: UNKNOWN
Project-URL: Source, https://github.com/TFDevCycle/MyHelp/
Project-URL: Bug Tracker, https://github.com/TFDevCycle/MyHelp/issues/
Platform: UNKNOWN
Classifier: Programming Language :: Python :: 3
Classifier: License :: OSI Approved :: MIT License
Classifier: Operating System :: OS Independent
Requires-Python: >=3.6
License-File: LICENSE
